MANIFEST.in
README.rst
setup.py
lode/__init__.py
lode.egg-info/PKG-INFO
lode.egg-info/SOURCES.txt
lode.egg-info/dependency_links.txt
lode.egg-info/top_level.txt