Metadata-Version: 1.1
Name: lode
Version: 0.2.2
Summary: Tiny and minimalistic logging utility
Home-page: https://github.com/kragniz/lode
Author: Louis Taylor
Author-email: kragniz@gmail.com
License: GPL
Keywords: logging debugging
Platform: UNKNOWN
Classifier: Development Status :: 3 - Alpha
Classifier: Intended Audience :: Developers
Classifier: License :: OSI Approved :: GNU General Public License v3 (GPLv3)
Classifier: Programming Language :: Python :: 2.6
Classifier: Programming Language :: Python :: 2.7
Classifier: Programming Language :: Python :: 3.2
Classifier: Programming Language :: Python :: 3.3
Classifier: Topic :: Software Development :: Debuggers
Classifier: Topic :: Software Development :: Libraries :: Python Modules
